Metadata-Version: 2.1
Name: simple-xls2json
Version: 1.0.4
Summary: Convert table data to json format output
Home-page: UNKNOWN
Author: Antiless
Author-email: antiless.dev@gmail.com
License: UNKNOWN
Keywords: xls json xlrd
Platform: UNKNOWN
